{
  "run_id": "20260120_115227",
  "train_days": 180,
  "test_days": 90,
  "min_test_bars": 300,
  "windows": 27,
  "equity_start": 10000.0,
  "equity_end": 9225.89420785135,
  "return_total_pct": -0.07741057921486494,
  "profit_factor_mean": 2.168248588153389,
  "profit_factor_median": 0.8119430619544747,
  "sharpe_mean": -0.8910261161597661,
  "dd_mean": -0.017771127376551305,
  "winrate_mean": 0.327795763906875,
  "entry_limit_fills_total": 195,
  "entry_fallback_market_total": 0,
  "config_used": {
    "adx_min_4h": 30.0,
    "adx_period": 14,
    "donchian_n": 20,
    "atr_period": 14,
    "atr_trail_mult": 3.0,
    "min_atr_ratio": 0.0015,
    "atr_exp_mult": 1.05,
    "breakout_buffer": 0.001,
    "pullback_max_wait_bars": 12,
    "pullback_fallback_market": false,
    "pullback_fallback_after_bars": 6,
    "sent_enabled": true,
    "fng_floor_mult": 0.1,
    "fee_bps": 7.5,
    "slippage_bps": 2.0,
    "direction": "both"
  },
  "note": "Walk-forward corre solo sobre ventanas TEST y encadena equity entre ventanas. Motor de ejecuci\u00f3n igual a 02_backtest.py v4.2."
}